myForceGauge/__init__.py
myForceGauge/myForceGauge.py
myForceGauge-0.0.3.dist-info/METADATA
myForceGauge-0.0.3.dist-info/WHEEL
myForceGauge-0.0.3.dist-info/top_level.txt
myForceGauge-0.0.3.dist-info/RECORD
